pgzero_template.py
pgzero_template-2.4.dist-info/LICENSE
pgzero_template-2.4.dist-info/METADATA
pgzero_template-2.4.dist-info/WHEEL
pgzero_template-2.4.dist-info/top_level.txt
pgzero_template-2.4.dist-info/RECORD
