Metadata-Version: 2.1
Name: pgzero-template
Version: 2.4
Summary: a template for pgzero
Home-page: https://github.com/zhec5hl01/python-games
Author: xiaofengkz
Author-email: xiaofengkz@163.com
License: MIT
Classifier: Topic :: Games/Entertainment 
Classifier: Topic :: Games/Entertainment :: Puzzle Games
Classifier: Topic :: Games/Entertainment :: Board Games
Classifier: Topic :: Software Development :: Libraries :: Python Modules
Classifier: Programming Language :: Python
Classifier: Programming Language :: Python :: 3
Classifier: Programming Language :: Python :: 3.5
Classifier: Programming Language :: Python :: 3.5
Classifier: Programming Language :: Python :: 3.6
Classifier: Programming Language :: Python :: 3.7
Classifier: Programming Language :: Python :: Implementation :: CPython
License-File: LICENSE
Requires-Dist: pgzero (<=1.2.1)
Requires-Dist: pygame (<=2.1.2)
